LICENSE
MANIFEST.in
README.rst
setup.cfg
setup.py
epipack/__init__.py
epipack/colors.py
epipack/distributions.py
epipack/integrators.py
epipack/interactive.py
epipack/metadata.py
epipack/mock_samplable_set.py
epipack/networks.py
epipack/numeric_epi_models.py
epipack/numeric_matrix_epi_models.py
epipack/plottools.py
epipack/process_conversions.py
epipack/stochastic_epi_models.py
epipack/symbolic_epi_models.py
epipack/symbolic_matrix_epi_models.py
epipack/temporal_networks.py
epipack/vis.py
epipack.egg-info/PKG-INFO
epipack.egg-info/SOURCES.txt
epipack.egg-info/dependency_links.txt
epipack.egg-info/not-zip-safe
epipack.egg-info/requires.txt
epipack.egg-info/top_level.txt
epipack/tests/SIR_weighted.py
epipack/tests/__init__.py
epipack/tests/conversion_tests.py
epipack/tests/distributions_tests.py
epipack/tests/integrator_tests.py
epipack/tests/interactive_tests.py
epipack/tests/mocksamplableset_tests.py
epipack/tests/network_tests.py
epipack/tests/numeric_matrix_based_tests.py
epipack/tests/numeric_tests.py
epipack/tests/stochastic_tests.py
epipack/tests/symbolic_matrix_tests.py
epipack/tests/symbolic_tests.py
epipack/tests/temporal_network_tests.py
epipack/tests/vis.py