Metadata-Version: 1.2
Name: epipack
Version: 0.1.5
Summary: Fast prototyping of epidemiological models based on reaction equations. Analyze the ODEs analytically or numerically, or run stochastic simulations on networks/well-mixed systems.
Home-page: https://github.com/benmaier/epipack
Author: Benjamin F. Maier
Author-email: contact@benmaier.org
License: MIT
Project-URL: Documentation, http://epipack.benmaier.org
Project-URL: Contributing Statement, https://github.com/benmaier/epipack/blob/master/CONTRIBUTING.md
Project-URL: Bug Reports, https://github.com/benmaier/epipack/issues
Project-URL: Source, https://github.com/benmaier/epipack/
Project-URL: PyPI, https://pypi.org/project/epipack/
Platform: UNKNOWN
Classifier: License :: OSI Approved :: MIT License
Classifier: Programming Language :: Python :: 3.6
Classifier: Programming Language :: Python :: 3.7
Classifier: Programming Language :: Python :: 3.8
Requires-Python: >=3.6
